git_rb/__init__.py
git_rb/main.py
git_rb-0.1.3.dist-info/METADATA
git_rb-0.1.3.dist-info/WHEEL
git_rb-0.1.3.dist-info/entry_points.txt
git_rb-0.1.3.dist-info/licenses/LICENSE
git_rb-0.1.3.dist-info/RECORD
