Metadata-Version: 2.4
Name: git-rb
Version: 0.1.3
Summary: Simple CLI for interactive git rebase workflow.
Project-URL: Homepage, https://github.com/geo7/git-rb
Project-URL: Repository, https://github.com/geo7/git-rb
Author-email: George Lenton <georgelenton@gmail.com>
License: MIT
License-File: LICENSE
Keywords: git,rebase,workflow
Requires-Python: ==3.13.4
Requires-Dist: rich>=14.0.0
Provides-Extra: dev
Requires-Dist: ipdb<0.14.0,>=0.13.9; extra == 'dev'
Requires-Dist: ipython>=8.18.1; extra == 'dev'
Requires-Dist: pdbpp<0.12.0,>=0.10.3; extra == 'dev'
Requires-Dist: pre-commit>=4.0.0; extra == 'dev'
Requires-Dist: pytest-cov>=5.0.0; extra == 'dev'
Requires-Dist: pytest<9.0.0,>=8.0.0; extra == 'dev'
Requires-Dist: ruff>=0.0.265; extra == 'dev'
Requires-Dist: ty>=0.0.1a13; extra == 'dev'
